{
  "kind": "collectionType",
  "collectionName": "videos",
  "info": {
    "name": "Video",
    "description": ""
  },
  "options": {
    "increments": true,
    "timestamps": true,
    "draftAndPublish": true
  },
  "pluginOptions": {
    "i18n": {
      "localized": true
    }
  },
  "attributes": {
    "PageSEO": {
      "type": "component",
      "repeatable": false,
      "pluginOptions": {
        "i18n": {
          "localized": true
        }
      },
      "component": "common.page-seo"
    },
    "VideoLandingPage": {
      "type": "component",
      "repeatable": false,
      "pluginOptions": {
        "i18n": {
          "localized": true
        }
      },
      "component": "video.video-landing-page"
    },
    "VideoSEO": {
      "type": "component",
      "repeatable": false,
      "pluginOptions": {
        "i18n": {
          "localized": true
        }
      },
      "component": "video.video-seo"
    },
    "VideoTitle": {
      "pluginOptions": {
        "i18n": {
          "localized": true
        }
      },
      "type": "string"
    },
    "slug": {
      "pluginOptions": {
        "i18n": {
          "localized": true
        }
      },
      "type": "string"
    },
    "Tag": {
      "pluginOptions": {
        "i18n": {
          "localized": true
        }
      },
      "type": "string"
    },
    "LatestVideoCTA": {
      "pluginOptions": {
        "i18n": {
          "localized": true
        }
      },
      "type": "string"
    }
  }
}
